[
    {
        "content": "<p>Who all are planning to attend Pycon 2020?</p>",
        "id": 184006714,
        "sender_full_name": "Vishnu Ks",
        "timestamp": 1576926738
    },
    {
        "content": "<p>I guess it's in Pittsburgh next year.  That definitely increases the chances I'll be there. <a href=\"https://us.pycon.org/2020/about/\" target=\"_blank\" title=\"https://us.pycon.org/2020/about/\">https://us.pycon.org/2020/about/</a></p>",
        "id": 184006839,
        "sender_full_name": "Steve Howell",
        "timestamp": 1576926968
    },
    {
        "content": "<p>I'd really like to go, but I'm not sure about cost or what I'll be doing then.</p>",
        "id": 184065591,
        "sender_full_name": "Neil Pilgrim",
        "timestamp": 1577041858
    },
    {
        "content": "<p>I really would like to attend pycon, but with graduation coming up I need the dust to settle in terms of starting my career, relocation, etc... So I'm shooting for my first pycon attendance to be in 2021.</p>",
        "id": 184069645,
        "sender_full_name": "Wyatt Hoodes",
        "timestamp": 1577049181
    }
]